deno_version_manager/__init__.py
deno_version_manager/__main__.py
deno_version_manager/main.py
deno_version_manager/test_main.py
deno_version_manager-0.1.0.dist-info/entry_points.txt
deno_version_manager-0.1.0.dist-info/WHEEL
deno_version_manager-0.1.0.dist-info/METADATA
deno_version_manager-0.1.0.dist-info/RECORD
