Metadata-Version: 2.1
Name: deno-version-manager
Version: 0.1.0
Summary: dvm - a cli to manage deno versions
Home-page: https://github.com/dev-124/dvm/
License: MIT
Keywords: version,manager,deno,denojs,dvm,cli
Author: dev-124
Author-email: 60511077+dev-124@users.noreply.github.com
Requires-Python: >=3.8,<4.0
Classifier: License :: OSI Approved :: MIT License
Classifier: Programming Language :: Python :: 3
Classifier: Programming Language :: Python :: 3.8
Classifier: Programming Language :: Python :: 3.9
Requires-Dist: black (>=21.7b0,<22.0)
Requires-Dist: coverage (>=5.5,<6.0)
Requires-Dist: mypy (>=0.910,<0.911)
Requires-Dist: pytest-cov (>=2.12.1,<3.0.0)
Requires-Dist: typer[all] (>=0.3.2,<0.4.0)
Project-URL: Repository, https://github.com/dev-124/dvm/
